django_todopago/__init__.py
django_todopago/admin.py
django_todopago/apps.py
django_todopago/models.py
django_todopago/urls.py
django_todopago/version.py
django_todopago/views.py
django_todopago/locale/es/LC_MESSAGES/django.mo
django_todopago/locale/es/LC_MESSAGES/django.po
django_todopago/migrations/0001_initial.py
django_todopago/migrations/0002_operationfailure.py
django_todopago/migrations/0003_operationpayment_payment_notnull.py
django_todopago/migrations/0004_operationfailure_answer_key.py
django_todopago/migrations/__init__.py
django_todopago/sdk/__init__.py
django_todopago/sdk/todopagoconnector.py
django_todopago/sdk/wsdl/Authorize.wsdl
django_todopago/sdk/wsdl/Operations.wsdl
django_todopago-0.1.1.dist-info/DESCRIPTION.rst
django_todopago-0.1.1.dist-info/METADATA
django_todopago-0.1.1.dist-info/RECORD
django_todopago-0.1.1.dist-info/WHEEL
django_todopago-0.1.1.dist-info/metadata.json
django_todopago-0.1.1.dist-info/top_level.txt
